Patterns/__init__.py
Patterns/pattern1.py
Patterns/pattern10.py
Patterns/pattern11.py
Patterns/pattern12.py
Patterns/pattern13.py
Patterns/pattern14.py
Patterns/pattern15.py
Patterns/pattern16.py
Patterns/pattern17.py
Patterns/pattern18.py
Patterns/pattern19.py
Patterns/pattern2.py
Patterns/pattern3.py
Patterns/pattern4.py
Patterns/pattern5.py
Patterns/pattern6.py
Patterns/pattern7.py
Patterns/pattern8.py
Patterns/pattern9.py
my_patterns-0.1.dist-info/LICENSE.txt
my_patterns-0.1.dist-info/METADATA
my_patterns-0.1.dist-info/WHEEL
my_patterns-0.1.dist-info/top_level.txt
my_patterns-0.1.dist-info/RECORD
