Metadata-Version: 2.1
Name: my_patterns
Version: 0.1
Summary: This Package for Python Patterns
Home-page: https://github.com/rdinesh808/py-codes
Author: rdinesh808
Author-email: rdinesh808@gmail.com
Classifier: Programming Language :: Python :: 3
Classifier: License :: OSI Approved :: MIT License
Classifier: Operating System :: OS Independent
Requires-Python: >=3.6
License-File: LICENSE.txt
